{
  "updated": "2026-07-07",
  "stocks": [
    {
      "ticker": "NVDA",
      "name": "NVIDIA Corp.",
      "price": 196.93,
      "change": "+0.71%",
      "changePositive": true,
      "marketCap": 4769841152000,
      "rank": 1
    },
    {
      "ticker": "AAPL",
      "name": "Apple Inc.",
      "price": 310.66,
      "change": "-0.64%",
      "changePositive": false,
      "marketCap": 4562774130688,
      "rank": 2
    },
    {
      "ticker": "GOOGL",
      "name": "Alphabet Inc. (Class A)",
      "price": 367.03,
      "change": "+0.16%",
      "changePositive": true,
      "marketCap": 4478710317056,
      "rank": 3
    },
    {
      "ticker": "GOOG",
      "name": "Alphabet Inc. (Class C)",
      "price": 363.62,
      "change": "-0.35%",
      "changePositive": false,
      "marketCap": 4437099675648,
      "rank": 4
    },
    {
      "ticker": "MSFT",
      "name": "Microsoft Corp.",
      "price": 388.84,
      "change": "+0.54%",
      "changePositive": true,
      "marketCap": 2888472723456,
      "rank": 5
    },
    {
      "ticker": "AMZN",
      "name": "Amazon.com Inc.",
      "price": 245.98,
      "change": "+0.75%",
      "changePositive": true,
      "marketCap": 2646033825792,
      "rank": 6
    },
    {
      "ticker": "AVGO",
      "name": "Broadcom Inc.",
      "price": 370.78,
      "change": "-0.83%",
      "changePositive": false,
      "marketCap": 1764015603712,
      "rank": 7
    },
    {
      "ticker": "META",
      "name": "Meta Platforms Inc.",
      "price": 615.58,
      "change": "+2.55%",
      "changePositive": true,
      "marketCap": 1562602635264,
      "rank": 8
    },
    {
      "ticker": "TSLA",
      "name": "Tesla Inc.",
      "price": 402.9,
      "change": "-4.02%",
      "changePositive": false,
      "marketCap": 1513181151232,
      "rank": 9
    },
    {
      "ticker": "LLY",
      "name": "Eli Lilly & Co.",
      "price": 1235.56,
      "change": "+2.96%",
      "changePositive": true,
      "marketCap": 1101800013824,
      "rank": 10
    },
    {
      "ticker": "BRK-A",
      "name": "Berkshire Hathaway (A)",
      "price": 756000.0,
      "change": "-0.13%",
      "changePositive": false,
      "marketCap": 1087054675968,
      "rank": 11
    },
    {
      "ticker": "BRK-B",
      "name": "Berkshire Hathaway (B)",
      "price": 504.0,
      "change": "-0.51%",
      "changePositive": false,
      "marketCap": 1087054282752,
      "rank": 12
    },
    {
      "ticker": "MU",
      "name": "Micron Technology",
      "price": 938.38,
      "change": "-4.71%",
      "changePositive": false,
      "marketCap": 1059799957504,
      "rank": 13
    }
  ]
}